{
 "absolute_value": 0,
 "align_labels_right": 0,
 "creation": "2024-07-01 15:53:35.152254",
 "css": ".print-format-preview {\n    background-color: var(--gray-200);\n}\n\n.zpl-label {\n    min-height: 4in;\n    max-height: 4in;\n    min-width: 6in;\n    max-width: 6in;\n    background-color: white;\n}\n\n.print-format {\n    max-width: unset;\n    min-height: unset;\n}\n\n.print-preview {\n    background: unset;\n}",
 "custom_format": 1,
 "default_print_language": "en",
 "disabled": 0,
 "doc_type": "Handling Unit",
 "docstatus": 0,
 "doctype": "Print Format",
 "font_size": 14,
 "html": "<div class=\"zpl-label\">\n<img src=\"data:image/png;base64,{{ labelary_api(doc, 'Handling Unit 6x4 ZPL Format', {}) }}\" />    \n</div>\n",
 "idx": 0,
 "line_breaks": 0,
 "margin_bottom": 15.0,
 "margin_left": 15.0,
 "margin_right": 15.0,
 "margin_top": 15.0,
 "modified": "2024-07-01 18:54:12.428312",
 "modified_by": "Administrator",
 "module": "BEAM",
 "name": "Labelary Print Preview",
 "owner": "Administrator",
 "page_number": "Hide",
 "print_format_builder": 0,
 "print_format_builder_beta": 0,
 "print_format_type": "Jinja",
 "raw_commands": "",
 "raw_printing": 0,
 "show_section_headings": 0,
 "standard": "Yes"
}